contentaiextractor/__init__.py
contentaiextractor-1.1.0.dist-info/LICENSE
contentaiextractor-1.1.0.dist-info/METADATA
contentaiextractor-1.1.0.dist-info/WHEEL
contentaiextractor-1.1.0.dist-info/top_level.txt
contentaiextractor-1.1.0.dist-info/RECORD
