Metadata-Version: 2.1
Name: contentaiextractor
Version: 1.1.0
Summary: makes it easier to implement a ContentAI extractor
Home-page: http://github.com/turnercode/contentai-extractor-runtime-python
Author: John Ritsema
Author-email: john.ritsema@turner.com
License: apache-2
Keywords: contentai extractor computervision cv ai ml
Platform: UNKNOWN
